vbvstatus/__init__.py
vbvstatus/vbvbin.txt
vbvstatus-0.1.0.dist-info/METADATA
vbvstatus-0.1.0.dist-info/WHEEL
vbvstatus-0.1.0.dist-info/entry_points.txt
vbvstatus-0.1.0.dist-info/top_level.txt
vbvstatus-0.1.0.dist-info/RECORD
