Metadata-Version: 2.4
Name: vbvstatus
Version: 0.1.0
Summary: A command-line tool and library for checking VBV status and performing BIN lookups.
Home-page: https://github.com/GunYamazakii/vbvstatus-pypi
Author: @unik_xd
Author-email: unik_xd@example.com
Classifier: Programming Language :: Python :: 3
Classifier: License :: OSI Approved :: MIT License
Classifier: Operating System :: OS Independent
Classifier: Development Status :: 3 - Alpha
Classifier: Topic :: Utilities
Requires-Python: >=3.6
Requires-Dist: requests
Dynamic: author
Dynamic: author-email
Dynamic: classifier
Dynamic: description
Dynamic: description-content-type
Dynamic: home-page
Dynamic: requires-dist
Dynamic: requires-python
Dynamic: summary
